MANIFEST.in
README.md
requirements.txt
setup.py
furozun/__init__.py
furozun/main.py
furozun.egg-info/PKG-INFO
furozun.egg-info/SOURCES.txt
furozun.egg-info/dependency_links.txt
furozun.egg-info/entry_points.txt
furozun.egg-info/not-zip-safe
furozun.egg-info/requires.txt
furozun.egg-info/top_level.txt
furozun/site_template/.furozun
furozun/site_template/build/.empty
furozun/site_template/pages/contact.md
furozun/site_template/pages/hello-blog.md
furozun/site_template/static/css/main.css
furozun/site_template/static/css/normalize.css
furozun/site_template/static/css/pygment.css
furozun/site_template/templates/base.html
furozun/site_template/templates/index.html
furozun/site_template/templates/page.html
furozun/site_template/templates/plain.html
furozun/site_template/templates/includes/header.html