Metadata-Version: 1.1
Name: furozun
Version: 0.0.1
Summary: Simple static site generator.
Home-page: https://github.com/amarsahinovic/furozun
Author: Amar Šahinović
Author-email: amar@sahinovic.com
License: BSD License
Platform: UNKNOWN
Classifier: Intended Audience :: Developers
Classifier: License :: OSI Approved :: BSD License
Classifier: Operating System :: OS Independent
Classifier: Programming Language :: Python
Classifier: Programming Language :: Python :: 2
Classifier: Programming Language :: Python :: 3
Classifier: Topic :: Utilities
